[
  {
    "id": 0,
    "source": "dataset-123",
    "value": 0.8224769161608296
  },
  {
    "id": 1,
    "source": "dataset-123",
    "value": 0.8164151226241965
  },
  {
    "id": 2,
    "source": "dataset-123",
    "value": 0.7485661190863389
  },
  {
    "id": 3,
    "source": "dataset-123",
    "value": 0.7516997674497468
  },
  {
    "id": 4,
    "source": "dataset-123",
    "value": 0.14492456374247276
  },
  {
    "id": 5,
    "source": "dataset-123",
    "value": 0.2896622675204992
  },
  {
    "id": 6,
    "source": "dataset-123",
    "value": 0.06417651945800618
  },
  {
    "id": 7,
    "source": "dataset-123",
    "value": 0.9668428515028555
  },
  {
    "id": 8,
    "source": "dataset-123",
    "value": 0.3860723400631285
  },
  {
    "id": 9,
    "source": "dataset-123",
    "value": 0.3378842785777989
  },
  {
    "id": 10,
    "source": "dataset-123",
    "value": 0.291883408126425
  },
  {
    "id": 11,
    "source": "dataset-123",
    "value": 0.7019396645283984
  },
  {
    "id": 12,
    "source": "dataset-123",
    "value": 0.1899126514707532
  },
  {
    "id": 13,
    "source": "dataset-123",
    "value": 0.4190312514141148
  },
  {
    "id": 14,
    "source": "dataset-123",
    "value": 0.06006685864687067
  },
  {
    "id": 15,
    "source": "dataset-123",
    "value": 0.662718153331276
  },
  {
    "id": 16,
    "source": "dataset-123",
    "value": 0.26960335847165395
  },
  {
    "id": 17,
    "source": "dataset-123",
    "value": 0.3274194893654778
  },
  {
    "id": 18,
    "source": "dataset-123",
    "value": 0.2821858371174064
  },
  {
    "id": 19,
    "source": "dataset-123",
    "value": 0.630236951044362
  },
  {
    "id": 20,
    "source": "dataset-123",
    "value": 0.7487857746209128
  },
  {
    "id": 21,
    "source": "dataset-123",
    "value": 0.32725409284781004
  },
  {
    "id": 22,
    "source": "dataset-123",
    "value": 0.8322743445043586
  },
  {
    "id": 23,
    "source": "dataset-123",
    "value": 0.6763830389503618
  },
  {
    "id": 24,
    "source": "dataset-123",
    "value": 0.9555494248456924
  },
  {
    "id": 25,
    "source": "dataset-123",
    "value": 0.12672382303804386
  },
  {
    "id": 26,
    "source": "dataset-123",
    "value": 0.022049762911565463
  },
  {
    "id": 27,
    "source": "dataset-123",
    "value": 0.7681553221486046
  },
  {
    "id": 28,
    "source": "dataset-123",
    "value": 0.5708957105644461
  },
  {
    "id": 29,
    "source": "dataset-123",
    "value": 0.8867448221471179
  },
  {
    "id": 30,
    "source": "dataset-123",
    "value": 0.8129831111147903
  },
  {
    "id": 31,
    "source": "dataset-123",
    "value": 0.5285414104882376
  },
  {
    "id": 32,
    "source": "dataset-123",
    "value": 0.2531201949414277
  }
]